exasol_keyphrase_vectorizers-1.0.0.data/data/requirements/requirements.txt
exasol_keyphrase_vectorizers-1.0.0.dist-info/licenses/LICENSE
keyphrase_vectorizers/__init__.py
keyphrase_vectorizers/_version.py
keyphrase_vectorizers/keyphrase_count_vectorizer.py
keyphrase_vectorizers/keyphrase_tfidf_vectorizer.py
keyphrase_vectorizers/keyphrase_vectorizer_mixin.py
tests/__init__.py
tests/test_vectorizers.py
tests/utils.py
exasol_keyphrase_vectorizers-1.0.0.dist-info/METADATA
exasol_keyphrase_vectorizers-1.0.0.dist-info/WHEEL
exasol_keyphrase_vectorizers-1.0.0.dist-info/top_level.txt
exasol_keyphrase_vectorizers-1.0.0.dist-info/RECORD
