Metadata-Version: 2.4
Name: exasol-keyphrase-vectorizers
Version: 1.0.0
Summary: Set of vectorizers that extract keyphrases with part-of-speech patterns from a collection of text documents and convert them into a document-keyphrase matrix.
Home-page: https://github.com/exasol/keyphrase-vectorizers
Author: Tim Schopf
Author-email: tim.schopf@t-online.de.de
License: BSD 3-Clause "New" or "Revised" License
Classifier: Development Status :: 3 - Alpha
Classifier: Programming Language :: Python :: 3
Classifier: Intended Audience :: Science/Research
Classifier: Intended Audience :: Developers
Classifier: Topic :: Scientific/Engineering :: Artificial Intelligence
Classifier: Topic :: Scientific/Engineering :: Information Analysis
Classifier: License :: OSI Approved :: BSD License
Classifier: Operating System :: OS Independent
Requires-Python: >=3.10
License-File: LICENSE
Requires-Dist: numpy>=1.18.5
Requires-Dist: spacy>=3.0.1
Requires-Dist: nltk>=3.6.1
Requires-Dist: scikit-learn>=1.0
Requires-Dist: scipy>=1.7.3
Requires-Dist: psutil>=5.8.0
Dynamic: author
Dynamic: author-email
Dynamic: classifier
Dynamic: description
Dynamic: description-content-type
Dynamic: home-page
Dynamic: license
Dynamic: license-file
Dynamic: requires-dist
Dynamic: requires-python
Dynamic: summary
